{
  "item02": {
    "backgroundColor": "#ffffff",
    "display": "list-item",
    "float": "left",
    "fontSize": "0rem",
    "height": "294rem",
    "lineHeight": "0rem",
    "marginLeft": "10rem",
    "position": "relative",
    "textAlign": "left",
    "verticalAlign": "top",
    "width": "186rem"
  },
  "imgWrap02": {
    "fontSize": "0rem",
    "height": "186rem",
    "lineHeight": "0rem",
    "overflow": "hidden",
    "position": "relative",
    "textAlign": "left",
    "width": "186rem"
  },
  "a21": {
    "color": "#0000ee",
    "display": "inline",
    "fontSize": "0rem",
    "lineHeight": "0rem",
    "textAlign": "left"
  },
  "J_LazyLoad": {
    "color": "#0000ee",
    "display": "inline",
    "fontSize": "0rem",
    "height": "186rem",
    "lineHeight": "0rem",
    "opacity": "0.9638414978981018",
    "textAlign": "left",
    "width": "186rem"
  },
  "itemFavorite02": {
    "backgroundColor": "rgba(0, 0, 0, 0.498039)",
    "bottom": "0rem",
    "color": "#ffffff",
    "fontSize": "13rem",
    "height": "23rem",
    "lineHeight": "23rem",
    "paddingLeft": "4rem",
    "paddingRight": "4rem",
    "position": "absolute",
    "right": "0rem",
    "textAlign": "center",
    "width": "85rem"
  },
  "itemTitle02": {
    "color": "#333333",
    "fontSize": "14rem",
    "height": "16rem",
    "lineHeight": "16rem",
    "marginTop": "9rem",
    "overflow": "hidden",
    "textAlign": "left",
    "width": "186rem"
  },
  "textNode59": {
    "color": "#333333",
    "display": "inline",
    "fontSize": "14rem",
    "lineHeight": "16rem",
    "marginLeft": "10rem",
    "textAlign": "left"
  },
  "itemCurrentPrice02": {
    "color": "#fc3342",
    "fontSize": "19rem",
    "height": "26rem",
    "lineHeight": "26rem",
    "marginLeft": "10rem",
    "marginTop": "4rem",
    "textAlign": "left",
    "verticalAlign": "bottom",
    "width": "176rem"
  },
  "jia1212": {
    "color": "#fc3342",
    "display": "inline",
    "fontSize": "19rem",
    "lineHeight": "26rem",
    "textAlign": "left"
  },
  "yen": {
    "color": "#fc3342",
    "display": "inline",
    "fontSize": "17rem",
    "lineHeight": "26rem",
    "textAlign": "left",
    "verticalAlign": "bottom"
  },
  "span1": {
    "color": "#fc3342",
    "display": "inline",
    "fontSize": "19rem",
    "lineHeight": "26rem",
    "textAlign": "left",
    "verticalAlign": "bottom"
  },
  "textNode84": {
    "color": "#fc3342",
    "display": "inline",
    "fontSize": "19rem",
    "lineHeight": "26rem",
    "textAlign": "left",
    "verticalAlign": "bottom"
  },
  "itemPrice02": {
    "color": "#b8b8b8",
    "fontSize": "13rem",
    "height": "13rem",
    "lineHeight": "13rem",
    "marginLeft": "10rem",
    "marginTop": "5rem",
    "textAlign": "left",
    "width": "176rem"
  },
  "textNode12": {
    "color": "#b8b8b8",
    "display": "inline",
    "fontSize": "13rem",
    "lineHeight": "13rem",
    "textAlign": "left",
    "textDecoration": "line-through"
  },
  "itemHongbao02": {
    "backgroundColor": "#fef0f0",
    "color": "#fc3342",
    "display": "inline-block",
    "fontSize": "13rem",
    "height": "30rem",
    "lineHeight": "30rem",
    "marginLeft": "10rem",
    "marginTop": "6rem",
    "overflow": "hidden",
    "textAlign": "center",
    "width": "94rem"
  },
  "itemBuy02": {
    "backgroundColor": "#fc3342",
    "color": "#ffffff",
    "display": "inline-block",
    "fontSize": "13rem",
    "height": "32rem",
    "lineHeight": "32rem",
    "marginLeft": "7rem",
    "marginTop": "6rem",
    "overflow": "hidden",
    "textAlign": "center",
    "width": "64rem"
  }
}